ttp_assistant/__init__.py
ttp_assistant/__main__.py
ttp_assistant/ace_and_term.py
ttp_assistant/qtwincon.html
ttp_assistant/qtwincon_widget.py
ttp_assistant/setup.py
ttp_assistant/ssh_history.yaml
ttp_assistant/Library/__init__.py
ttp_assistant/Library/assitant.py
ttp_assistant/Library/contextMenus.py
ttp_assistant/Library/customTE.py
ttp_assistant/Library/editor.py
ttp_assistant/Library/editor_handler.py
ttp_assistant/Library/mdi_util.py
ttp_assistant/Library/ttpfire.py
ttp_assistant/Library/utils.py
ttp_assistant/Library/winschemahandler.py
ttp_assistant/Library/winshell.py
ttp_assistant/Library/winshellreader.py
ttp_assistant/Library/__pycache__/__init__.cpython-39.pyc
ttp_assistant/Library/__pycache__/customTE.cpython-39.pyc
ttp_assistant/Library/__pycache__/editor.cpython-39.pyc
ttp_assistant/Library/__pycache__/editor_handler.cpython-39.pyc
ttp_assistant/Library/__pycache__/mdi_util.cpython-39.pyc
ttp_assistant/Library/__pycache__/utils.cpython-39.pyc
ttp_assistant/Library/__pycache__/winschemahandler.cpython-39.pyc
ttp_assistant/Library/__pycache__/winshell.cpython-39.pyc
ttp_assistant/Library/__pycache__/winshellreader.cpython-39.pyc
ttp_assistant/ace/editor.html
ttp_assistant/ace/editor_custom.js
ttp_assistant/ace/qcstuff.js
ttp_assistant/ace/qtchan.js
ttp_assistant/ace/css/ace.css
ttp_assistant/ace/css/ambiance-1.png
ttp_assistant/ace/css/ambiance-2.png
ttp_assistant/ace/css/ambiance-3.png
ttp_assistant/ace/css/chrome-1.png
ttp_assistant/ace/css/chrome-2.png
ttp_assistant/ace/css/cloud9_day-1.png
ttp_assistant/ace/css/cloud9_day-2.png
ttp_assistant/ace/css/cloud9_night-1.png
ttp_assistant/ace/css/cloud9_night-2.png
ttp_assistant/ace/css/cloud9_night_low_color-1.png
ttp_assistant/ace/css/cloud9_night_low_color-2.png
ttp_assistant/ace/css/clouds-1.png
ttp_assistant/ace/css/clouds-2.png
ttp_assistant/ace/css/clouds_midnight-1.png
ttp_assistant/ace/css/clouds_midnight-2.png
ttp_assistant/ace/css/cobalt-1.png
ttp_assistant/ace/css/cobalt-2.png
ttp_assistant-0.1.0.dist-info/METADATA
ttp_assistant-0.1.0.dist-info/WHEEL
ttp_assistant-0.1.0.dist-info/entry_points.txt
ttp_assistant-0.1.0.dist-info/top_level.txt
ttp_assistant-0.1.0.dist-info/RECORD
