Metadata-Version: 2.1
Name: ttp_assistant
Version: 0.1.0
Summary: A tool to assist with TTP template building in a GUI, testing and execution
Home-page: https://github.com/scottpeterman/ttpassistant
Author: Scott Peterman
Author-email: scottpeterman@gmail.com
License: GPLv3
Project-URL: Bug Tracker, https://github.com/scottpeterman/ttpassistant/issues
Project-URL: Source Code, https://github.com/scottpeterman/ttpassistant
Classifier: Development Status :: 3 - Alpha
Classifier: Intended Audience :: Developers
Classifier: Intended Audience :: Information Technology
Classifier: License :: OSI Approved :: GNU General Public License v3 (GPLv3)
Classifier: Operating System :: OS Independent
Classifier: Programming Language :: Python :: 3.9
Classifier: Programming Language :: Python :: 3.10
Classifier: Programming Language :: Python :: 3.11
Classifier: Topic :: Software Development :: Libraries :: Python Modules
Classifier: Topic :: System :: Networking
Requires-Python: >=3.9
Requires-Dist: bcrypt>=4.2.0
Requires-Dist: cffi>=1.17.1
Requires-Dist: click>=8.1.7
Requires-Dist: colorama>=0.4.6
Requires-Dist: cryptography>=43.0.3
Requires-Dist: Jinja2>=3.1.4
Requires-Dist: jmespath>=1.0.1
Requires-Dist: MarkupSafe>=3.0.1
Requires-Dist: paramiko>=3.5.0
Requires-Dist: pycparser>=2.22
Requires-Dist: PyNaCl>=1.5.0
Requires-Dist: PyQt6>=6.7.1
Requires-Dist: PyQt6-Qt6>=6.7.3
Requires-Dist: PyQt6-WebEngine>=6.7.0
Requires-Dist: PyQt6-WebEngine-Qt6>=6.7.3
Requires-Dist: PyQt6-WebEngineSubwheel-Qt6>=6.7.3
Requires-Dist: PyQt6-sip>=13.8.0
Requires-Dist: pysshpass>=0.2.2
Requires-Dist: pywinpty>=2.0.14
Requires-Dist: PyYAML>=6.0.2
Requires-Dist: ruamel.yaml>=0.18.6
Requires-Dist: ruamel.yaml.clib>=0.2.8
Requires-Dist: tabulate>=0.9.0
Requires-Dist: ttp>=0.9.5
